CHANGES.txt
MANIFEST.in
Makefile
README.txt
ez_setup.py
runtests.py
setup.py
version.txt
src/__init__.py
src/evogrid/__init__.py
src/evogrid/interfaces.py
src/evogrid/testing.py
src/evogrid/tests.py
src/evogrid.egg-info/PKG-INFO
src/evogrid.egg-info/SOURCES.txt
src/evogrid.egg-info/dependency_links.txt
src/evogrid.egg-info/not-zip-safe
src/evogrid.egg-info/requires.txt
src/evogrid.egg-info/top_level.txt
src/evogrid/caching/README.txt
src/evogrid/caching/__init__.py
src/evogrid/caching/interfaces.py
src/evogrid/caching/memcached.py
src/evogrid/caching/ram.py
src/evogrid/caching/tests.py
src/evogrid/common/README.txt
src/evogrid/common/__init__.py
src/evogrid/common/checkpointers.py
src/evogrid/common/comparators.py
src/evogrid/common/evaluators.py
src/evogrid/common/evolvers.py
src/evogrid/common/pools.py
src/evogrid/common/providers.py
src/evogrid/common/replacers.py
src/evogrid/common/replicators.py
src/evogrid/common/selectors.py
src/evogrid/common/variators.py
src/evogrid/common/tests/__init__.py
src/evogrid/common/tests/test_checkpointers.txt
src/evogrid/common/tests/test_comparators.py
src/evogrid/common/tests/test_doctests.py
src/evogrid/common/tests/test_elite_archive.txt
src/evogrid/common/tests/test_evaluators.py
src/evogrid/common/tests/test_evolvers.txt
src/evogrid/common/tests/test_pools.py
src/evogrid/common/tests/test_replacers.py
src/evogrid/common/tests/test_replicators.txt
src/evogrid/common/tests/test_selectors.py
src/evogrid/common/tests/test_variators.py
src/evogrid/mo/README.txt
src/evogrid/mo/__init__.py
src/evogrid/mo/comparators.py
src/evogrid/mo/interfaces.py
src/evogrid/mo/tests.py
src/evogrid/numeric/README.txt
src/evogrid/numeric/__init__.py
src/evogrid/numeric/dejong.py
src/evogrid/numeric/domains.py
src/evogrid/numeric/interfaces.py
src/evogrid/numeric/plot.py
src/evogrid/numeric/providers.py
src/evogrid/numeric/replicators.py
src/evogrid/numeric/variators.py
src/evogrid/numeric/tests/__init__.py
src/evogrid/numeric/tests/test_dejong.py
src/evogrid/numeric/tests/test_readme.py
src/evogrid/numeric/tests/test_variators.py
src/evogrid/sharing/README.txt
src/evogrid/sharing/__init__.py
src/evogrid/sharing/comparators.py
