Metadata-Version: 1.0
Name: evogrid
Version: 0.1.0
Summary: Distributed Evolutionary Computation framework
Home-page: http://champiland.homelinux.net/evogrid/doc
Author: Olivier Grisel
Author-email: olivier.grisel@ensta.org
License: GNU GPL v2
Download-URL: http://cheeseshop.python.org/pypi/evogrid
Platform: UNKNOWN
Classifier: Development Status :: 3 - Alpha
Classifier: Environment :: Console
Classifier: Intended Audience :: Developers
Classifier: License :: OSI Approved :: GNU General Public License (GPL)
Classifier: Operating System :: OS Independent
Classifier: Programming Language :: Python
